{
	"number_result": 22,
	"results": [{
		"accuracy": 4,
		"proj4": "+proj=lcc +lat_1=47.33333333333334 +lat_2=45.83333333333334 +lat_0=45.33333333333334 +lon_0=-120.5 +x_0=500000 +y_0=0 +ellps=GRS80 +towgs84=0,0,0,0,0,0,0 +units=m +no_defs",
		"code": "32149",
		"name": "NAD83 / Washington South",
		"area": "United States (USA) - Washington - counties of Adams; Asotin; Benton; Clark; Columbia; Cowlitz; Franklin; Garfield; Grant south of approximately 47°30'N; Grays Harbor; Kittitas; Klickitat; Lewis; Mason; Pacific; Pierce; Skamania; Thurston; Wahkiakum; Walla Walla; Whitman; Yakima.",
		"bbox": [47.61,
		-124.4,
		45.54,
		-116.91],
		"trans": [1188,
		1251,
		1252,
		1308,
		1515,
		15835,
		15837,
		15839,
		1696,
		1697,
		1702,
		1708,
		1709,
		1710,
		1711,
		1712,
		1713,
		1714,
		1715,
		1716,
		1717,
		1718,
		1719,
		1720,
		1721,
		1722,
		1723,
		1724,
		1725,
		1726,
		1727,
		1728,
		1729,
		1730,
		1731,
		1732,
		1733,
		1734,
		1735,
		1736,
		1737,
		1738,
		1739,
		1740,
		1741,
		1742,
		1743,
		1744,
		1745,
		1746,
		1747,
		1748,
		1749,
		1750,
		8421,
		8422,
		8566],
		"wkt": "PROJCS[\"NAD83 / Washington South\",GEOGCS[\"NAD83\",DATUM[\"North_American_Datum_1983\",SPHEROID[\"GRS 1980\",6378137,298.257222101,AUTHORITY[\"EPSG\",\"7019\"]],TOWGS84[0,0,0,0,0,0,0],AUTHORITY[\"EPSG\",\"6269\"]],PRIMEM[\"Greenwich\",0,AUTHORITY[\"EPSG\",\"8901\"]],UNIT[\"degree\",0.0174532925199433,AUTHORITY[\"EPSG\",\"9122\"]],AUTHORITY[\"EPSG\",\"4269\"]],PROJECTION[\"Lambert_Conformal_Conic_2SP\"],PARAMETER[\"standard_parallel_1\",47.33333333333334],PARAMETER[\"standard_parallel_2\",45.83333333333334],PARAMETER[\"latitude_of_origin\",45.33333333333334],PARAMETER[\"central_meridian\",-120.5],PARAMETER[\"false_easting\",500000],PARAMETER[\"false_northing\",0],UNIT[\"metre\",1,AUTHORITY[\"EPSG\",\"9001\"]],AXIS[\"X\",EAST],AXIS[\"Y\",NORTH],AUTHORITY[\"EPSG\",\"32149\"]]",
		"kind": "CRS-PROJCRS",
		"default_trans": 1188
	},
	{
		"accuracy": 4,
		"proj4": "+proj=lcc +lat_1=48.73333333333333 +lat_2=47.5 +lat_0=47 +lon_0=-120.8333333333333 +x_0=500000 +y_0=0 +ellps=GRS80 +towgs84=0,0,0,0,0,0,0 +units=m +no_defs",
		"code": "32148",
		"name": "NAD83 / Washington North",
		"area": "United States (USA) - Washington - counties of Chelan; Clallam; Douglas; Ferry; Grant north of approximately 47°30'N; Island; Jefferson; King; Kitsap; Lincoln; Okanogan; Pend Oreille; San Juan; Skagit; Snohomish; Spokane; Stevens; Whatcom.",
		"bbox": [49.05,
		-124.79,
		47.08,
		-117.02],
		"trans": [1188,
		1251,
		1252,
		1308,
		1515,
		15835,
		15837,
		15839,
		1696,
		1697,
		1702,
		1708,
		1709,
		1710,
		1711,
		1712,
		1713,
		1714,
		1715,
		1716,
		1717,
		1718,
		1719,
		1720,
		1721,
		1722,
		1723,
		1724,
		1725,
		1726,
		1727,
		1728,
		1729,
		1730,
		1731,
		1732,
		1733,
		1734,
		1735,
		1736,
		1737,
		1738,
		1739,
		1740,
		1741,
		1742,
		1743,
		1744,
		1745,
		1746,
		1747,
		1748,
		1749,
		1750,
		8421,
		8422,
		8566],
		"wkt": "PROJCS[\"NAD83 / Washington North\",GEOGCS[\"NAD83\",DATUM[\"North_American_Datum_1983\",SPHEROID[\"GRS 1980\",6378137,298.257222101,AUTHORITY[\"EPSG\",\"7019\"]],TOWGS84[0,0,0,0,0,0,0],AUTHORITY[\"EPSG\",\"6269\"]],PRIMEM[\"Greenwich\",0,AUTHORITY[\"EPSG\",\"8901\"]],UNIT[\"degree\",0.0174532925199433,AUTHORITY[\"EPSG\",\"9122\"]],AUTHORITY[\"EPSG\",\"4269\"]],PROJECTION[\"Lambert_Conformal_Conic_2SP\"],PARAMETER[\"standard_parallel_1\",48.73333333333333],PARAMETER[\"standard_parallel_2\",47.5],PARAMETER[\"latitude_of_origin\",47],PARAMETER[\"central_meridian\",-120.8333333333333],PARAMETER[\"false_easting\",500000],PARAMETER[\"false_northing\",0],UNIT[\"metre\",1,AUTHORITY[\"EPSG\",\"9001\"]],AXIS[\"X\",EAST],AXIS[\"Y\",NORTH],AUTHORITY[\"EPSG\",\"32148\"]]",
		"kind": "CRS-PROJCRS",
		"default_trans": 1188
	},
	{
		"accuracy": "",
		"proj4": "+proj=lcc +lat_1=45.83333333333334 +lat_2=47.33333333333334 +lat_0=45.33333333333334 +lon_0=-120.5 +x_0=609601.2192024384 +y_0=0 +datum=NAD27 +units=us-ft +no_defs",
		"code": "32049",
		"name": "NAD27 / Washington South",
		"area": "United States (USA) - Washington - counties of Adams; Asotin; Benton; Clark; Columbia; Cowlitz; Franklin; Garfield; Grant; Grays Harbor; Kittitas; Klickitat; Lewis; Mason; Pacific; Pierce; Skamania; Thurston; Wahkiakum; Walla Walla; Whitman; Yakima.",
		"bbox": [47.96,
		-124.4,
		45.54,
		-116.91],
		"trans": [1170,
		1171,
		1172,
		1173,
		1174,
		1175,
		1176,
		1177,
		1178,
		1179,
		1180,
		1181,
		1182,
		1183,
		1184,
		1185,
		1186,
		1187,
		1249,
		1250,
		1530,
		15699,
		15851,
		15852,
		15853,
		15854,
		15855,
		15856,
		15864,
		15913,
		15978,
		1692,
		1693,
		1703,
		8243,
		8245,
		8404,
		8420,
		8496,
		8497,
		8565,
		8585,
		8590,
		8591,
		8592,
		8593,
		8594,
		8595,
		8596,
		8597,
		8598,
		8599,
		8600,
		8601,
		8602,
		8603,
		8604,
		8605,
		8606,
		8607,
		8608,
		8609,
		8610,
		8611,
		8612,
		8613,
		8614,
		8615,
		8616,
		8617,
		8618,
		8619,
		8620,
		8621,
		8622,
		8623,
		8624,
		8625,
		8626,
		8627,
		8628,
		8629,
		8630,
		8647],
		"wkt": "PROJCS[\"NAD27 / Washington South\",GEOGCS[\"NAD27\",DATUM[\"North_American_Datum_1927\",SPHEROID[\"Clarke 1866\",6378206.4,294.9786982139006,AUTHORITY[\"EPSG\",\"7008\"]],AUTHORITY[\"EPSG\",\"6267\"]],PRIMEM[\"Greenwich\",0,AUTHORITY[\"EPSG\",\"8901\"]],UNIT[\"degree\",0.0174532925199433,AUTHORITY[\"EPSG\",\"9122\"]],AUTHORITY[\"EPSG\",\"4267\"]],PROJECTION[\"Lambert_Conformal_Conic_2SP\"],PARAMETER[\"standard_parallel_1\",45.83333333333334],PARAMETER[\"standard_parallel_2\",47.33333333333334],PARAMETER[\"latitude_of_origin\",45.33333333333334],PARAMETER[\"central_meridian\",-120.5],PARAMETER[\"false_easting\",2000000],PARAMETER[\"false_northing\",0],UNIT[\"US survey foot\",0.3048006096012192,AUTHORITY[\"EPSG\",\"9003\"]],AXIS[\"X\",EAST],AXIS[\"Y\",NORTH],AUTHORITY[\"EPSG\",\"32049\"]]",
		"kind": "CRS-PROJCRS",
		"default_trans": 0
	},
	{
		"accuracy": "",
		"proj4": "+proj=lcc +lat_1=47.5 +lat_2=48.73333333333333 +lat_0=47 +lon_0=-120.8333333333333 +x_0=609601.2192024384 +y_0=0 +datum=NAD27 +units=us-ft +no_defs",
		"code": "32048",
		"name": "NAD27 / Washington North",
		"area": "United States (USA) - Washington - counties of Chelan; Clallam; Douglas; Ferry; Island; Jefferson; King; Kitsap; Lincoln; Okanogan; Pend Oreille; San Juan; Skagit; Snohomish; Spokane; Stevens; Whatcom.",
		"bbox": [49.05,
		-124.79,
		47.08,
		-117.02],
		"trans": [1170,
		1171,
		1172,
		1173,
		1174,
		1175,
		1176,
		1177,
		1178,
		1179,
		1180,
		1181,
		1182,
		1183,
		1184,
		1185,
		1186,
		1187,
		1249,
		1250,
		1530,
		15699,
		15851,
		15852,
		15853,
		15854,
		15855,
		15856,
		15864,
		15913,
		15978,
		1692,
		1693,
		1703,
		8243,
		8245,
		8404,
		8420,
		8496,
		8497,
		8565,
		8585,
		8590,
		8591,
		8592,
		8593,
		8594,
		8595,
		8596,
		8597,
		8598,
		8599,
		8600,
		8601,
		8602,
		8603,
		8604,
		8605,
		8606,
		8607,
		8608,
		8609,
		8610,
		8611,
		8612,
		8613,
		8614,
		8615,
		8616,
		8617,
		8618,
		8619,
		8620,
		8621,
		8622,
		8623,
		8624,
		8625,
		8626,
		8627,
		8628,
		8629,
		8630,
		8647],
		"wkt": "PROJCS[\"NAD27 / Washington North\",GEOGCS[\"NAD27\",DATUM[\"North_American_Datum_1927\",SPHEROID[\"Clarke 1866\",6378206.4,294.9786982139006,AUTHORITY[\"EPSG\",\"7008\"]],AUTHORITY[\"EPSG\",\"6267\"]],PRIMEM[\"Greenwich\",0,AUTHORITY[\"EPSG\",\"8901\"]],UNIT[\"degree\",0.0174532925199433,AUTHORITY[\"EPSG\",\"9122\"]],AUTHORITY[\"EPSG\",\"4267\"]],PROJECTION[\"Lambert_Conformal_Conic_2SP\"],PARAMETER[\"standard_parallel_1\",47.5],PARAMETER[\"standard_parallel_2\",48.73333333333333],PARAMETER[\"latitude_of_origin\",47],PARAMETER[\"central_meridian\",-120.8333333333333],PARAMETER[\"false_easting\",2000000],PARAMETER[\"false_northing\",0],UNIT[\"US survey foot\",0.3048006096012192,AUTHORITY[\"EPSG\",\"9003\"]],AXIS[\"X\",EAST],AXIS[\"Y\",NORTH],AUTHORITY[\"EPSG\",\"32048\"]]",
		"kind": "CRS-PROJCRS",
		"default_trans": 0
	},
	{
		"accuracy": "",
		"proj4": "",
		"code": "6598",
		"name": "NAD83(2011) / Washington South",
		"area": "United States (USA) - Washington - counties of Adams; Asotin; Benton; Clark; Columbia; Cowlitz; Franklin; Garfield; Grant south of approximately 47°30'N; Grays Harbor; Kittitas; Klickitat; Lewis; Mason; Pacific; Pierce; Skamania; Thurston; Wahkiakum; Walla Walla; Whitman; Yakima.",
		"bbox": [47.61,
		-124.4,
		45.54,
		-116.91],
		"trans": [],
		"wkt": "",
		"kind": "CRS-PROJCRS",
		"default_trans": 0
	},
	{
		"accuracy": "",
		"proj4": "",
		"code": "6596",
		"name": "NAD83(2011) / Washington North",
		"area": "United States (USA) - Washington - counties of Chelan; Clallam; Douglas; Ferry; Grant north of approximately 47°30'N; Island; Jefferson; King; Kitsap; Lincoln; Okanogan; Pend Oreille; San Juan; Skagit; Snohomish; Spokane; Stevens; Whatcom.",
		"bbox": [49.05,
		-124.79,
		47.08,
		-117.02],
		"trans": [],
		"wkt": "",
		"kind": "CRS-PROJCRS",
		"default_trans": 0
	},
	{
		"accuracy": 1,
		"proj4": "+proj=lcc +lat_1=47.33333333333334 +lat_2=45.83333333333334 +lat_0=45.33333333333334 +lon_0=-120.5 +x_0=500000 +y_0=0 +ellps=GRS80 +towgs84=0,0,0,0,0,0,0 +units=m +no_defs",
		"code": "3691",
		"name": "NAD83(NSRS2007) / Washington South",
		"area": "United States (USA) - Washington - counties of Adams; Asotin; Benton; Clark; Columbia; Cowlitz; Franklin; Garfield; Grant south of approximately 47°30'N; Grays Harbor; Kittitas; Klickitat; Lewis; Mason; Pacific; Pierce; Skamania; Thurston; Wahkiakum; Walla Walla; Whitman; Yakima.",
		"bbox": [47.61,
		-124.4,
		45.54,
		-116.91],
		"trans": [15931],
		"wkt": "PROJCS[\"NAD83(NSRS2007) / Washington South\",GEOGCS[\"NAD83(NSRS2007)\",DATUM[\"NAD83_National_Spatial_Reference_System_2007\",SPHEROID[\"GRS 1980\",6378137,298.257222101,AUTHORITY[\"EPSG\",\"7019\"]],TOWGS84[0,0,0,0,0,0,0],AUTHORITY[\"EPSG\",\"6759\"]],PRIMEM[\"Greenwich\",0,AUTHORITY[\"EPSG\",\"8901\"]],UNIT[\"degree\",0.0174532925199433,AUTHORITY[\"EPSG\",\"9122\"]],AUTHORITY[\"EPSG\",\"4759\"]],PROJECTION[\"Lambert_Conformal_Conic_2SP\"],PARAMETER[\"standard_parallel_1\",47.33333333333334],PARAMETER[\"standard_parallel_2\",45.83333333333334],PARAMETER[\"latitude_of_origin\",45.33333333333334],PARAMETER[\"central_meridian\",-120.5],PARAMETER[\"false_easting\",500000],PARAMETER[\"false_northing\",0],UNIT[\"metre\",1,AUTHORITY[\"EPSG\",\"9001\"]],AXIS[\"X\",EAST],AXIS[\"Y\",NORTH],AUTHORITY[\"EPSG\",\"3691\"]]",
		"kind": "CRS-PROJCRS",
		"default_trans": 15931
	},
	{
		"accuracy": 1,
		"proj4": "+proj=lcc +lat_1=48.73333333333333 +lat_2=47.5 +lat_0=47 +lon_0=-120.8333333333333 +x_0=500000 +y_0=0 +ellps=GRS80 +towgs84=0,0,0,0,0,0,0 +units=m +no_defs",
		"code": "3689",
		"name": "NAD83(NSRS2007) / Washington North",
		"area": "United States (USA) - Washington - counties of Chelan; Clallam; Douglas; Ferry; Grant north of approximately 47°30'N; Island; Jefferson; King; Kitsap; Lincoln; Okanogan; Pend Oreille; San Juan; Skagit; Snohomish; Spokane; Stevens; Whatcom.",
		"bbox": [49.05,
		-124.79,
		47.08,
		-117.02],
		"trans": [15931],
		"wkt": "PROJCS[\"NAD83(NSRS2007) / Washington North\",GEOGCS[\"NAD83(NSRS2007)\",DATUM[\"NAD83_National_Spatial_Reference_System_2007\",SPHEROID[\"GRS 1980\",6378137,298.257222101,AUTHORITY[\"EPSG\",\"7019\"]],TOWGS84[0,0,0,0,0,0,0],AUTHORITY[\"EPSG\",\"6759\"]],PRIMEM[\"Greenwich\",0,AUTHORITY[\"EPSG\",\"8901\"]],UNIT[\"degree\",0.0174532925199433,AUTHORITY[\"EPSG\",\"9122\"]],AUTHORITY[\"EPSG\",\"4759\"]],PROJECTION[\"Lambert_Conformal_Conic_2SP\"],PARAMETER[\"standard_parallel_1\",48.73333333333333],PARAMETER[\"standard_parallel_2\",47.5],PARAMETER[\"latitude_of_origin\",47],PARAMETER[\"central_meridian\",-120.8333333333333],PARAMETER[\"false_easting\",500000],PARAMETER[\"false_northing\",0],UNIT[\"metre\",1,AUTHORITY[\"EPSG\",\"9001\"]],AXIS[\"X\",EAST],AXIS[\"Y\",NORTH],AUTHORITY[\"EPSG\",\"3689\"]]",
		"kind": "CRS-PROJCRS",
		"default_trans": 15931
	},
	{
		"accuracy": 0.1,
		"proj4": "+proj=lcc +lat_1=47.33333333333334 +lat_2=45.83333333333334 +lat_0=45.33333333333334 +lon_0=-120.5 +x_0=500000 +y_0=0 +ellps=GRS80 +towgs84=0,0,0,0,0,0,0 +units=m +no_defs",
		"code": "2856",
		"name": "NAD83(HARN) / Washington South",
		"area": "United States (USA) - Washington - counties of Adams; Asotin; Benton; Clark; Columbia; Cowlitz; Franklin; Garfield; Grant south of approximately 47°30'N; Grays Harbor; Kittitas; Klickitat; Lewis; Mason; Pacific; Pierce; Skamania; Thurston; Wahkiakum; Walla Walla; Whitman; Yakima.",
		"bbox": [47.61,
		-124.4,
		45.54,
		-116.91],
		"trans": [1580,
		15930,
		1900,
		1901],
		"wkt": "PROJCS[\"NAD83(HARN) / Washington South\",GEOGCS[\"NAD83(HARN)\",DATUM[\"NAD83_High_Accuracy_Reference_Network\",SPHEROID[\"GRS 1980\",6378137,298.257222101,AUTHORITY[\"EPSG\",\"7019\"]],TOWGS84[0,0,0,0,0,0,0],AUTHORITY[\"EPSG\",\"6152\"]],PRIMEM[\"Greenwich\",0,AUTHORITY[\"EPSG\",\"8901\"]],UNIT[\"degree\",0.0174532925199433,AUTHORITY[\"EPSG\",\"9122\"]],AUTHORITY[\"EPSG\",\"4152\"]],PROJECTION[\"Lambert_Conformal_Conic_2SP\"],PARAMETER[\"standard_parallel_1\",47.33333333333334],PARAMETER[\"standard_parallel_2\",45.83333333333334],PARAMETER[\"latitude_of_origin\",45.33333333333334],PARAMETER[\"central_meridian\",-120.5],PARAMETER[\"false_easting\",500000],PARAMETER[\"false_northing\",0],UNIT[\"metre\",1,AUTHORITY[\"EPSG\",\"9001\"]],AXIS[\"X\",EAST],AXIS[\"Y\",NORTH],AUTHORITY[\"EPSG\",\"2856\"]]",
		"kind": "CRS-PROJCRS",
		"default_trans": 15930
	},
	{
		"accuracy": 0.1,
		"proj4": "+proj=lcc +lat_1=48.73333333333333 +lat_2=47.5 +lat_0=47 +lon_0=-120.8333333333333 +x_0=500000 +y_0=0 +ellps=GRS80 +towgs84=0,0,0,0,0,0,0 +units=m +no_defs",
		"code": "2855",
		"name": "NAD83(HARN) / Washington North",
		"area": "United States (USA) - Washington - counties of Chelan; Clallam; Douglas; Ferry; Grant north of approximately 47°30'N; Island; Jefferson; King; Kitsap; Lincoln; Okanogan; Pend Oreille; San Juan; Skagit; Snohomish; Spokane; Stevens; Whatcom.",
		"bbox": [49.05,
		-124.79,
		47.08,
		-117.02],
		"trans": [1580,
		15930,
		1900,
		1901],
		"wkt": "PROJCS[\"NAD83(HARN) / Washington North\",GEOGCS[\"NAD83(HARN)\",DATUM[\"NAD83_High_Accuracy_Reference_Network\",SPHEROID[\"GRS 1980\",6378137,298.257222101,AUTHORITY[\"EPSG\",\"7019\"]],TOWGS84[0,0,0,0,0,0,0],AUTHORITY[\"EPSG\",\"6152\"]],PRIMEM[\"Greenwich\",0,AUTHORITY[\"EPSG\",\"8901\"]],UNIT[\"degree\",0.0174532925199433,AUTHORITY[\"EPSG\",\"9122\"]],AUTHORITY[\"EPSG\",\"4152\"]],PROJECTION[\"Lambert_Conformal_Conic_2SP\"],PARAMETER[\"standard_parallel_1\",48.73333333333333],PARAMETER[\"standard_parallel_2\",47.5],PARAMETER[\"latitude_of_origin\",47],PARAMETER[\"central_meridian\",-120.8333333333333],PARAMETER[\"false_easting\",500000],PARAMETER[\"false_northing\",0],UNIT[\"metre\",1,AUTHORITY[\"EPSG\",\"9001\"]],AXIS[\"X\",EAST],AXIS[\"Y\",NORTH],AUTHORITY[\"EPSG\",\"2855\"]]",
		"kind": "CRS-PROJCRS",
		"default_trans": 15930
	},
	{
		"accuracy": 4.0,
		"proj4": "+proj=lcc +lat_1=47.33333333333334 +lat_2=45.83333333333334 +lat_0=45.33333333333334 +lon_0=-120.5 +x_0=500000.0001016001 +y_0=0 +ellps=GRS80 +towgs84=0,0,0,0,0,0,0 +units=us-ft +no_defs",
		"code": "2286",
		"name": "NAD83 / Washington South (ftUS)",
		"area": "United States (USA) - Washington - counties of Adams; Asotin; Benton; Clark; Columbia; Cowlitz; Franklin; Garfield; Grant south of approximately 47\u00b030'N; Grays Harbor; Kittitas; Klickitat; Lewis; Mason; Pacific; Pierce; Skamania; Thurston; Wahkiakum; Walla Walla; Whitman; Yakima.",
		"bbox": [47.61,
		-124.4,
		45.54,
		-116.91],
		"trans": [1188,
		1251,
		1252,
		1308,
		1515,
		15835,
		15837,
		15839,
		1696,
		1697,
		1702,
		1708,
		1709,
		1710,
		1711,
		1712,
		1713,
		1714,
		1715,
		1716,
		1717,
		1718,
		1719,
		1720,
		1721,
		1722,
		1723,
		1724,
		1725,
		1726,
		1727,
		1728,
		1729,
		1730,
		1731,
		1732,
		1733,
		1734,
		1735,
		1736,
		1737,
		1738,
		1739,
		1740,
		1741,
		1742,
		1743,
		1744,
		1745,
		1746,
		1747,
		1748,
		1749,
		1750,
		8421,
		8422,
		8566],
		"wkt": "PROJCS[\"NAD83 / Washington South (ftUS)\",GEOGCS[\"NAD83\",DATUM[\"North_American_Datum_1983\",SPHEROID[\"GRS 1980\",6378137,298.257222101,AUTHORITY[\"EPSG\",\"7019\"]],TOWGS84[0,0,0,0,0,0,0],AUTHORITY[\"EPSG\",\"6269\"]],PRIMEM[\"Greenwich\",0,AUTHORITY[\"EPSG\",\"8901\"]],UNIT[\"degree\",0.0174532925199433,AUTHORITY[\"EPSG\",\"9122\"]],AUTHORITY[\"EPSG\",\"4269\"]],PROJECTION[\"Lambert_Conformal_Conic_2SP\"],PARAMETER[\"standard_parallel_1\",47.33333333333334],PARAMETER[\"standard_parallel_2\",45.83333333333334],PARAMETER[\"latitude_of_origin\",45.33333333333334],PARAMETER[\"central_meridian\",-120.5],PARAMETER[\"false_easting\",1640416.667],PARAMETER[\"false_northing\",0],UNIT[\"US survey foot\",0.3048006096012192,AUTHORITY[\"EPSG\",\"9003\"]],AXIS[\"X\",EAST],AXIS[\"Y\",NORTH],AUTHORITY[\"EPSG\",\"2286\"]]",
		"kind": "CRS-PROJCRS",
		"default_trans": 1188
	},
	{
		"accuracy": 4.0,
		"proj4": "+proj=lcc +lat_1=48.73333333333333 +lat_2=47.5 +lat_0=47 +lon_0=-120.8333333333333 +x_0=500000.0001016001 +y_0=0 +ellps=GRS80 +towgs84=0,0,0,0,0,0,0 +units=us-ft +no_defs",
		"code": "2285",
		"name": "NAD83 / Washington North (ftUS)",
		"area": "United States (USA) - Washington - counties of Chelan; Clallam; Douglas; Ferry; Grant north of approximately 47\u00b030'N; Island; Jefferson; King; Kitsap; Lincoln; Okanogan; Pend Oreille; San Juan; Skagit; Snohomish; Spokane; Stevens; Whatcom.",
		"bbox": [49.05,
		-124.79,
		47.08,
		-117.02],
		"trans": [1188,
		1251,
		1252,
		1308,
		1515,
		15835,
		15837,
		15839,
		1696,
		1697,
		1702,
		1708,
		1709,
		1710,
		1711,
		1712,
		1713,
		1714,
		1715,
		1716,
		1717,
		1718,
		1719,
		1720,
		1721,
		1722,
		1723,
		1724,
		1725,
		1726,
		1727,
		1728,
		1729,
		1730,
		1731,
		1732,
		1733,
		1734,
		1735,
		1736,
		1737,
		1738,
		1739,
		1740,
		1741,
		1742,
		1743,
		1744,
		1745,
		1746,
		1747,
		1748,
		1749,
		1750,
		8421,
		8422,
		8566],
		"wkt": "PROJCS[\"NAD83 / Washington North (ftUS)\",GEOGCS[\"NAD83\",DATUM[\"North_American_Datum_1983\",SPHEROID[\"GRS 1980\",6378137,298.257222101,AUTHORITY[\"EPSG\",\"7019\"]],TOWGS84[0,0,0,0,0,0,0],AUTHORITY[\"EPSG\",\"6269\"]],PRIMEM[\"Greenwich\",0,AUTHORITY[\"EPSG\",\"8901\"]],UNIT[\"degree\",0.0174532925199433,AUTHORITY[\"EPSG\",\"9122\"]],AUTHORITY[\"EPSG\",\"4269\"]],PROJECTION[\"Lambert_Conformal_Conic_2SP\"],PARAMETER[\"standard_parallel_1\",48.73333333333333],PARAMETER[\"standard_parallel_2\",47.5],PARAMETER[\"latitude_of_origin\",47],PARAMETER[\"central_meridian\",-120.8333333333333],PARAMETER[\"false_easting\",1640416.667],PARAMETER[\"false_northing\",0],UNIT[\"US survey foot\",0.3048006096012192,AUTHORITY[\"EPSG\",\"9003\"]],AXIS[\"X\",EAST],AXIS[\"Y\",NORTH],AUTHORITY[\"EPSG\",\"2285\"]]",
		"kind": "CRS-PROJCRS",
		"default_trans": 1188
	},
	{
		"accuracy": "",
		"proj4": "",
		"code": "6599",
		"name": "NAD83(2011) / Washington South (ftUS)",
		"area": "United States (USA) - Washington - counties of Adams; Asotin; Benton; Clark; Columbia; Cowlitz; Franklin; Garfield; Grant south of approximately 47\u00b030'N; Grays Harbor; Kittitas; Klickitat; Lewis; Mason; Pacific; Pierce; Skamania; Thurston; Wahkiakum; Walla Walla; Whitman; Yakima.",
		"bbox": [47.61,
		-124.4,
		45.54,
		-116.91],
		"trans": [],
		"wkt": "",
		"kind": "CRS-PROJCRS",
		"default_trans": 0
	},
	{
		"accuracy": "",
		"proj4": "",
		"code": "6597",
		"name": "NAD83(2011) / Washington North (ftUS)",
		"area": "United States (USA) - Washington - counties of Chelan; Clallam; Douglas; Ferry; Grant north of approximately 47\u00b030'N; Island; Jefferson; King; Kitsap; Lincoln; Okanogan; Pend Oreille; San Juan; Skagit; Snohomish; Spokane; Stevens; Whatcom.",
		"bbox": [49.05,
		-124.79,
		47.08,
		-117.02],
		"trans": [],
		"wkt": "",
		"kind": "CRS-PROJCRS",
		"default_trans": 0
	},
	{
		"accuracy": 1.0,
		"proj4": "+proj=lcc +lat_1=47.33333333333334 +lat_2=45.83333333333334 +lat_0=45.33333333333334 +lon_0=-120.5 +x_0=500000.0001016001 +y_0=0 +ellps=GRS80 +towgs84=0,0,0,0,0,0,0 +units=us-ft +no_defs",
		"code": "3692",
		"name": "NAD83(NSRS2007) / Washington South (ftUS)",
		"area": "United States (USA) - Washington - counties of Adams; Asotin; Benton; Clark; Columbia; Cowlitz; Franklin; Garfield; Grant south of approximately 47\u00b030'N; Grays Harbor; Kittitas; Klickitat; Lewis; Mason; Pacific; Pierce; Skamania; Thurston; Wahkiakum; Walla Walla; Whitman; Yakima.",
		"bbox": [47.61,
		-124.4,
		45.54,
		-116.91],
		"trans": [15931],
		"wkt": "PROJCS[\"NAD83(NSRS2007) / Washington South (ftUS)\",GEOGCS[\"NAD83(NSRS2007)\",DATUM[\"NAD83_National_Spatial_Reference_System_2007\",SPHEROID[\"GRS 1980\",6378137,298.257222101,AUTHORITY[\"EPSG\",\"7019\"]],TOWGS84[0,0,0,0,0,0,0],AUTHORITY[\"EPSG\",\"6759\"]],PRIMEM[\"Greenwich\",0,AUTHORITY[\"EPSG\",\"8901\"]],UNIT[\"degree\",0.0174532925199433,AUTHORITY[\"EPSG\",\"9122\"]],AUTHORITY[\"EPSG\",\"4759\"]],PROJECTION[\"Lambert_Conformal_Conic_2SP\"],PARAMETER[\"standard_parallel_1\",47.33333333333334],PARAMETER[\"standard_parallel_2\",45.83333333333334],PARAMETER[\"latitude_of_origin\",45.33333333333334],PARAMETER[\"central_meridian\",-120.5],PARAMETER[\"false_easting\",1640416.667],PARAMETER[\"false_northing\",0],UNIT[\"US survey foot\",0.3048006096012192,AUTHORITY[\"EPSG\",\"9003\"]],AXIS[\"X\",EAST],AXIS[\"Y\",NORTH],AUTHORITY[\"EPSG\",\"3692\"]]",
		"kind": "CRS-PROJCRS",
		"default_trans": 15931
	},
	{
		"accuracy": 1.0,
		"proj4": "+proj=lcc +lat_1=48.73333333333333 +lat_2=47.5 +lat_0=47 +lon_0=-120.8333333333333 +x_0=500000.0001016001 +y_0=0 +ellps=GRS80 +towgs84=0,0,0,0,0,0,0 +units=us-ft +no_defs",
		"code": "3690",
		"name": "NAD83(NSRS2007) / Washington North (ftUS)",
		"area": "United States (USA) - Washington - counties of Chelan; Clallam; Douglas; Ferry; Grant north of approximately 47\u00b030'N; Island; Jefferson; King; Kitsap; Lincoln; Okanogan; Pend Oreille; San Juan; Skagit; Snohomish; Spokane; Stevens; Whatcom.",
		"bbox": [49.05,
		-124.79,
		47.08,
		-117.02],
		"trans": [15931],
		"wkt": "PROJCS[\"NAD83(NSRS2007) / Washington North (ftUS)\",GEOGCS[\"NAD83(NSRS2007)\",DATUM[\"NAD83_National_Spatial_Reference_System_2007\",SPHEROID[\"GRS 1980\",6378137,298.257222101,AUTHORITY[\"EPSG\",\"7019\"]],TOWGS84[0,0,0,0,0,0,0],AUTHORITY[\"EPSG\",\"6759\"]],PRIMEM[\"Greenwich\",0,AUTHORITY[\"EPSG\",\"8901\"]],UNIT[\"degree\",0.0174532925199433,AUTHORITY[\"EPSG\",\"9122\"]],AUTHORITY[\"EPSG\",\"4759\"]],PROJECTION[\"Lambert_Conformal_Conic_2SP\"],PARAMETER[\"standard_parallel_1\",48.73333333333333],PARAMETER[\"standard_parallel_2\",47.5],PARAMETER[\"latitude_of_origin\",47],PARAMETER[\"central_meridian\",-120.8333333333333],PARAMETER[\"false_easting\",1640416.667],PARAMETER[\"false_northing\",0],UNIT[\"US survey foot\",0.3048006096012192,AUTHORITY[\"EPSG\",\"9003\"]],AXIS[\"X\",EAST],AXIS[\"Y\",NORTH],AUTHORITY[\"EPSG\",\"3690\"]]",
		"kind": "CRS-PROJCRS",
		"default_trans": 15931
	},
	{
		"accuracy": 0.1,
		"proj4": "+proj=lcc +lat_1=47.33333333333334 +lat_2=45.83333333333334 +lat_0=45.33333333333334 +lon_0=-120.5 +x_0=500000.0001016001 +y_0=0 +ellps=GRS80 +towgs84=0,0,0,0,0,0,0 +units=us-ft +no_defs",
		"code": "2927",
		"name": "NAD83(HARN) / Washington South (ftUS)",
		"area": "United States (USA) - Washington - counties of Adams; Asotin; Benton; Clark; Columbia; Cowlitz; Franklin; Garfield; Grant south of approximately 47\u00b030'N; Grays Harbor; Kittitas; Klickitat; Lewis; Mason; Pacific; Pierce; Skamania; Thurston; Wahkiakum; Walla Walla; Whitman; Yakima.",
		"bbox": [47.61,
		-124.4,
		45.54,
		-116.91],
		"trans": [1580,
		15930,
		1900,
		1901],
		"wkt": "PROJCS[\"NAD83(HARN) / Washington South (ftUS)\",GEOGCS[\"NAD83(HARN)\",DATUM[\"NAD83_High_Accuracy_Reference_Network\",SPHEROID[\"GRS 1980\",6378137,298.257222101,AUTHORITY[\"EPSG\",\"7019\"]],TOWGS84[0,0,0,0,0,0,0],AUTHORITY[\"EPSG\",\"6152\"]],PRIMEM[\"Greenwich\",0,AUTHORITY[\"EPSG\",\"8901\"]],UNIT[\"degree\",0.0174532925199433,AUTHORITY[\"EPSG\",\"9122\"]],AUTHORITY[\"EPSG\",\"4152\"]],PROJECTION[\"Lambert_Conformal_Conic_2SP\"],PARAMETER[\"standard_parallel_1\",47.33333333333334],PARAMETER[\"standard_parallel_2\",45.83333333333334],PARAMETER[\"latitude_of_origin\",45.33333333333334],PARAMETER[\"central_meridian\",-120.5],PARAMETER[\"false_easting\",1640416.667],PARAMETER[\"false_northing\",0],UNIT[\"US survey foot\",0.3048006096012192,AUTHORITY[\"EPSG\",\"9003\"]],AXIS[\"X\",EAST],AXIS[\"Y\",NORTH],AUTHORITY[\"EPSG\",\"2927\"]]",
		"kind": "CRS-PROJCRS",
		"default_trans": 15930
	},
	{
		"accuracy": 0.1,
		"proj4": "+proj=lcc +lat_1=48.73333333333333 +lat_2=47.5 +lat_0=47 +lon_0=-120.8333333333333 +x_0=500000.0001016001 +y_0=0 +ellps=GRS80 +towgs84=0,0,0,0,0,0,0 +units=us-ft +no_defs",
		"code": "2926",
		"name": "NAD83(HARN) / Washington North (ftUS)",
		"area": "United States (USA) - Washington - counties of Chelan; Clallam; Douglas; Ferry; Grant north of approximately 47\u00b030'N; Island; Jefferson; King; Kitsap; Lincoln; Okanogan; Pend Oreille; San Juan; Skagit; Snohomish; Spokane; Stevens; Whatcom.",
		"bbox": [49.05,
		-124.79,
		47.08,
		-117.02],
		"trans": [1580,
		15930,
		1900,
		1901],
		"wkt": "PROJCS[\"NAD83(HARN) / Washington North (ftUS)\",GEOGCS[\"NAD83(HARN)\",DATUM[\"NAD83_High_Accuracy_Reference_Network\",SPHEROID[\"GRS 1980\",6378137,298.257222101,AUTHORITY[\"EPSG\",\"7019\"]],TOWGS84[0,0,0,0,0,0,0],AUTHORITY[\"EPSG\",\"6152\"]],PRIMEM[\"Greenwich\",0,AUTHORITY[\"EPSG\",\"8901\"]],UNIT[\"degree\",0.0174532925199433,AUTHORITY[\"EPSG\",\"9122\"]],AUTHORITY[\"EPSG\",\"4152\"]],PROJECTION[\"Lambert_Conformal_Conic_2SP\"],PARAMETER[\"standard_parallel_1\",48.73333333333333],PARAMETER[\"standard_parallel_2\",47.5],PARAMETER[\"latitude_of_origin\",47],PARAMETER[\"central_meridian\",-120.8333333333333],PARAMETER[\"false_easting\",1640416.667],PARAMETER[\"false_northing\",0],UNIT[\"US survey foot\",0.3048006096012192,AUTHORITY[\"EPSG\",\"9003\"]],AXIS[\"X\",EAST],AXIS[\"Y\",NORTH],AUTHORITY[\"EPSG\",\"2926\"]]",
		"kind": "CRS-PROJCRS",
		"default_trans": 15930
	},
	{
		"accuracy": "",
		"proj4": "+proj=lcc +lat_1=45.83333333333334 +lat_2=47.33333333333334 +lat_0=45.33333333333334 +lon_0=-120.5 +x_0=500000.0000000002 +y_0=0 +datum=NAD83 +units=us-ft +no_defs",
		"code": "102749",
		"name": "NAD 1983 StatePlane Washington South FIPS 4602 Feet",
		"area": "",
		"bbox": "",
		"trans": [],
		"wkt": "PROJCS[\"NAD_1983_StatePlane_Washington_South_FIPS_4602_Feet\",GEOGCS[\"GCS_North_American_1983\",DATUM[\"North_American_Datum_1983\",SPHEROID[\"GRS_1980\",6378137,298.257222101]],PRIMEM[\"Greenwich\",0],UNIT[\"Degree\",0.017453292519943295]],PROJECTION[\"Lambert_Conformal_Conic_2SP\"],PARAMETER[\"False_Easting\",1640416.666666667],PARAMETER[\"False_Northing\",0],PARAMETER[\"Central_Meridian\",-120.5],PARAMETER[\"Standard_Parallel_1\",45.83333333333334],PARAMETER[\"Standard_Parallel_2\",47.33333333333334],PARAMETER[\"Latitude_Of_Origin\",45.33333333333334],UNIT[\"Foot_US\",0.30480060960121924],AUTHORITY[\"EPSG\",\"102749\"]]",
		"kind": "CRS-PROJCRS",
		"default_trans": 0
	},
	{
		"accuracy": "",
		"proj4": "+proj=lcc +lat_1=47.5 +lat_2=48.73333333333333 +lat_0=47 +lon_0=-120.8333333333333 +x_0=500000.0000000002 +y_0=0 +datum=NAD83 +units=us-ft +no_defs",
		"code": "102748",
		"name": "NAD 1983 StatePlane Washington North FIPS 4601 Feet",
		"area": "",
		"bbox": "",
		"trans": [],
		"wkt": "PROJCS[\"NAD_1983_StatePlane_Washington_North_FIPS_4601_Feet\",GEOGCS[\"GCS_North_American_1983\",DATUM[\"North_American_Datum_1983\",SPHEROID[\"GRS_1980\",6378137,298.257222101]],PRIMEM[\"Greenwich\",0],UNIT[\"Degree\",0.017453292519943295]],PROJECTION[\"Lambert_Conformal_Conic_2SP\"],PARAMETER[\"False_Easting\",1640416.666666667],PARAMETER[\"False_Northing\",0],PARAMETER[\"Central_Meridian\",-120.8333333333333],PARAMETER[\"Standard_Parallel_1\",47.5],PARAMETER[\"Standard_Parallel_2\",48.73333333333333],PARAMETER[\"Latitude_Of_Origin\",47],UNIT[\"Foot_US\",0.30480060960121924],AUTHORITY[\"EPSG\",\"102748\"]]",
		"kind": "CRS-PROJCRS",
		"default_trans": 0
	},
	{
		"accuracy": "",
		"proj4": "+proj=lcc +lat_1=45.83333333333334 +lat_2=47.33333333333334 +lat_0=45.33333333333334 +lon_0=-120.5 +x_0=500000 +y_0=0 +ellps=GRS80 +units=m +no_defs",
		"code": "102349",
		"name": "NAD 1983 HARN StatePlane Washington South FIPS 4602",
		"area": "",
		"bbox": "",
		"trans": [],
		"wkt": "PROJCS[\"NAD_1983_HARN_StatePlane_Washington_South_FIPS_4602\",GEOGCS[\"GCS_North_American_1983_HARN\",DATUM[\"NAD83_High_Accuracy_Regional_Network\",SPHEROID[\"GRS_1980\",6378137,298.257222101]],PRIMEM[\"Greenwich\",0],UNIT[\"Degree\",0.017453292519943295]],PROJECTION[\"Lambert_Conformal_Conic_2SP\"],PARAMETER[\"False_Easting\",500000],PARAMETER[\"False_Northing\",0],PARAMETER[\"Central_Meridian\",-120.5],PARAMETER[\"Standard_Parallel_1\",45.83333333333334],PARAMETER[\"Standard_Parallel_2\",47.33333333333334],PARAMETER[\"Latitude_Of_Origin\",45.33333333333334],UNIT[\"Meter\",1],AUTHORITY[\"EPSG\",\"102349\"]]",
		"kind": "CRS-PROJCRS",
		"default_trans": 0
	},
	{
		"accuracy": "",
		"proj4": "+proj=lcc +lat_1=47.5 +lat_2=48.73333333333333 +lat_0=47 +lon_0=-120.8333333333333 +x_0=500000 +y_0=0 +ellps=GRS80 +units=m +no_defs",
		"code": "102348",
		"name": "NAD 1983 HARN StatePlane Washington North FIPS 4601",
		"area": "",
		"bbox": "",
		"trans": [],
		"wkt": "PROJCS[\"NAD_1983_HARN_StatePlane_Washington_North_FIPS_4601\",GEOGCS[\"GCS_North_American_1983_HARN\",DATUM[\"NAD83_High_Accuracy_Regional_Network\",SPHEROID[\"GRS_1980\",6378137,298.257222101]],PRIMEM[\"Greenwich\",0],UNIT[\"Degree\",0.017453292519943295]],PROJECTION[\"Lambert_Conformal_Conic_2SP\"],PARAMETER[\"False_Easting\",500000],PARAMETER[\"False_Northing\",0],PARAMETER[\"Central_Meridian\",-120.8333333333333],PARAMETER[\"Standard_Parallel_1\",47.5],PARAMETER[\"Standard_Parallel_2\",48.73333333333333],PARAMETER[\"Latitude_Of_Origin\",47],UNIT[\"Meter\",1],AUTHORITY[\"EPSG\",\"102348\"]]",
		"kind": "CRS-PROJCRS",
		"default_trans": 0
	}]
}